{
  "kind": "singleType",
  "collectionName": "events_pages",
  "info": {
    "singularName": "events-page",
    "pluralName": "events-pages",
    "displayName": "EventsPage",
    "description": ""
  },
  "options": {
    "draftAndPublish": false
  },
  "pluginOptions": {
    "i18n": {
      "localized": true
    }
  },
  "attributes": {
    "pageContent": {
      "type": "dynamiczone",
      "components": [
        "components.footer",
        "events.header",
        "components.cta"
      ],
      "pluginOptions": {
        "i18n": {
          "localized": true
        }
      }
    },
    "seo": {
      "type": "component",
      "repeatable": false,
      "pluginOptions": {
        "i18n": {
          "localized": true
        }
      },
      "component": "shared.seo"
    }
  }
}
